./.gitignore
./PKG-INFO
./README.md
./__init__.py
./pyproject.toml
./test.py
./video_hash.py
feluda_video_hash-0.1.1.dist-info/METADATA
feluda_video_hash-0.1.1.dist-info/WHEEL
feluda_video_hash-0.1.1.dist-info/RECORD
